effectual/__init__.py
effectual/build.py
effectual/colors.py
effectual/config.py
effectual/developer.py
effectual/lib.py
effectual/transformations.py
effectual-0.8.7.dist-info/METADATA
effectual-0.8.7.dist-info/WHEEL
effectual-0.8.7.dist-info/entry_points.txt
effectual-0.8.7.dist-info/licenses/LICENSE
effectual-0.8.7.dist-info/RECORD
