Metadata-Version: 2.4
Name: effectual
Version: 0.8.7
Summary: A python package/script bundler
Project-URL: Homepage, https://github.com/effectualpy/effectual
Author-email: jake <jakewdr@proton.me>
License-Expression: MIT
License-File: LICENSE
Classifier: Programming Language :: Python :: 3.9
Classifier: Programming Language :: Python :: 3.10
Classifier: Programming Language :: Python :: 3.11
Classifier: Programming Language :: Python :: 3.12
Classifier: Programming Language :: Python :: 3.13
Classifier: Programming Language :: Python :: 3.14
Classifier: Programming Language :: Python :: Implementation :: CPython
Requires-Python: >=3.9
Requires-Dist: click>=8.1.7
Requires-Dist: python-minifier>=2.11.3
Requires-Dist: rtoml>=0.11.0
Requires-Dist: termcolor>=2.4.0
Requires-Dist: watchfiles>=0.24.0
